paddleocr/__init__.py
paddleocr/__main__.py
paddleocr/_abstract.py
paddleocr/_cli.py
paddleocr/_common_args.py
paddleocr/_constants.py
paddleocr/_env.py
paddleocr/_version.py
paddleocr/_models/__init__.py
paddleocr/_models/_doc_vlm.py
paddleocr/_models/_image_classification.py
paddleocr/_models/_object_detection.py
paddleocr/_models/_text_detection.py
paddleocr/_models/base.py
paddleocr/_models/chart_parsing.py
paddleocr/_models/doc_img_orientation_classification.py
paddleocr/_models/doc_vlm.py
paddleocr/_models/formula_recognition.py
paddleocr/_models/layout_detection.py
paddleocr/_models/seal_text_detection.py
paddleocr/_models/table_cells_detection.py
paddleocr/_models/table_classification.py
paddleocr/_models/table_structure_recognition.py
paddleocr/_models/text_detection.py
paddleocr/_models/text_image_unwarping.py
paddleocr/_models/text_recognition.py
paddleocr/_models/textline_orientation_classification.py
paddleocr/_pipelines/__init__.py
paddleocr/_pipelines/base.py
paddleocr/_pipelines/doc_preprocessor.py
paddleocr/_pipelines/doc_understanding.py
paddleocr/_pipelines/formula_recognition.py
paddleocr/_pipelines/ocr.py
paddleocr/_pipelines/paddleocr_vl.py
paddleocr/_pipelines/pp_chatocrv4_doc.py
paddleocr/_pipelines/pp_doctranslation.py
paddleocr/_pipelines/pp_structurev3.py
paddleocr/_pipelines/seal_recognition.py
paddleocr/_pipelines/table_recognition_v2.py
paddleocr/_pipelines/utils.py
paddleocr/_utils/__init__.py
paddleocr/_utils/cli.py
paddleocr/_utils/deprecation.py
paddleocr/_utils/logging.py
paddleocr-3.3.3.dist-info/LICENSE
paddleocr-3.3.3.dist-info/METADATA
paddleocr-3.3.3.dist-info/WHEEL
paddleocr-3.3.3.dist-info/entry_points.txt
paddleocr-3.3.3.dist-info/top_level.txt
paddleocr-3.3.3.dist-info/RECORD
