Metadata-Version: 2.1
Name: paddleocr
Version: 3.3.3
Summary: Awesome multilingual OCR and document parsing toolkits based on PaddlePaddle
Author-email: PaddlePaddle <paddleocr@baidu.com>
Maintainer-email: PaddlePaddle <paddleocr@baidu.com>
License: Apache License 2.0
Project-URL: homepage, https://github.com/PaddlePaddle/PaddleOCR
Project-URL: documentation, https://github.com/PaddlePaddle/PaddleOCR/blob/main/README.md
Project-URL: repository, https://github.com/PaddlePaddle/PaddleOCR.git
Project-URL: issues, https://github.com/PaddlePaddle/PaddleOCR/issues
Keywords: ocr,textdetection,textrecognition,paddleocr,chineseocr,pp-ocr,pp-structure,document-parsing,pdf2markdown,kie,pp-chatocr,document-translation,rag
Classifier: Intended Audience :: Developers
Classifier: Operating System :: OS Independent
Classifier: Natural Language :: Chinese (Simplified)
Classifier: Programming Language :: Python :: 3
Classifier: Topic :: Utilities
Requires-Python: >=3.8
License-File: LICENSE
Requires-Dist: paddlex[ocr-core]<3.4.0,>=3.3.0
Requires-Dist: PyYAML>=6
Requires-Dist: requests
Requires-Dist: typing-extensions>=4.12
Provides-Extra: all
Requires-Dist: paddlex[genai-client,ie,ocr,trans]<3.4.0,>=3.3.0; extra == "all"
Provides-Extra: doc-parser
Requires-Dist: paddlex[genai-client,ocr]<3.4.0,>=3.3.0; extra == "doc-parser"
Provides-Extra: ie
Requires-Dist: paddlex[ie]<3.4.0,>=3.3.0; extra == "ie"
Provides-Extra: trans
Requires-Dist: paddlex[trans]<3.4.0,>=3.3.0; extra == "trans"
